example_server/server_client_example.py
example_server/server_example.py
examples/cli.py
examples/example_scripts/check_audio_devices.py
examples/example_scripts/client_example.py
examples/example_scripts/debug_openai.py
examples/example_scripts/openai_only.py
examples/example_scripts/transcribe.py
examples/example_scripts/wake_word_example.py
realtime_mlx_stt/README.md
realtime_mlx_stt/__init__.py
realtime_mlx_stt/client.py
realtime_mlx_stt/config.py
realtime_mlx_stt/session.py
realtime_mlx_stt/transcriber.py
realtime_mlx_stt/types.py
realtime_mlx_stt/utils.py
realtime_mlx_stt/wake_word.py
realtime_mlx_stt-0.1.5.dist-info/licenses/LICENSE
scripts/change_log_level.py
src/__init__.py
src/Application/__init__.py
src/Application/Server/ServerModule.py
src/Application/Server/__init__.py
src/Application/Server/Configuration/ProfileManager.py
src/Application/Server/Configuration/ServerConfig.py
src/Application/Server/Configuration/__init__.py
src/Application/Server/Controllers/BaseController.py
src/Application/Server/Controllers/SystemController.py
src/Application/Server/Controllers/TranscriptionController.py
src/Application/Server/Controllers/__init__.py
src/Application/Server/Models/SystemModels.py
src/Application/Server/Models/TranscriptionModels.py
src/Application/Server/Models/__init__.py
src/Application/Server/WebSocket/WebSocketManager.py
src/Application/Server/WebSocket/__init__.py
src/Core/__init__.py
src/Core/Commands/__init__.py
src/Core/Commands/command.py
src/Core/Commands/command_dispatcher.py
src/Core/Common/__init__.py
src/Core/Common/Interfaces/__init__.py
src/Core/Common/Interfaces/audio_provider.py
src/Core/Common/Interfaces/command_handler.py
src/Core/Common/Interfaces/event_bus.py
src/Core/Common/Interfaces/transcription_engine.py
src/Core/Common/Interfaces/voice_activity_detector.py
src/Core/Common/Interfaces/wake_word_detector.py
src/Core/Events/__init__.py
src/Core/Events/event.py
src/Core/Events/event_bus.py
src/Features/__init__.py
src/Features/AudioCapture/AudioCaptureModule.py
realtime_mlx_stt-0.1.5.dist-info/METADATA
realtime_mlx_stt-0.1.5.dist-info/WHEEL
realtime_mlx_stt-0.1.5.dist-info/top_level.txt
realtime_mlx_stt-0.1.5.dist-info/RECORD
