Metadata-Version: 2.4
Name: realtime-mlx-stt
Version: 0.1.5
Summary: Real-time speech-to-text transcription optimized for Apple Silicon
Author-email: Kristoffer Vatnehol <kristoffer.vatnehol@gmail.com>
License-Expression: MIT
Project-URL: Homepage, https://github.com/kristofferv98/Realtime_mlx_STT
Project-URL: Repository, https://github.com/kristofferv98/Realtime_mlx_STT
Project-URL: Issues, https://github.com/kristofferv98/Realtime_mlx_STT/issues
Keywords: speech-to-text,stt,transcription,whisper,mlx,apple-silicon,real-time,voice-activity-detection,vad,wake-word,speech-recognition,audio-processing,macos,m1,m2,m3,neural-engine
Classifier: Development Status :: 3 - Alpha
Classifier: Intended Audience :: Developers
Classifier: Programming Language :: Python :: 3
Classifier: Programming Language :: Python :: 3.9
Classifier: Programming Language :: Python :: 3.10
Classifier: Programming Language :: Python :: 3.11
Classifier: Programming Language :: Python :: 3.12
Classifier: Topic :: Scientific/Engineering :: Artificial Intelligence
Classifier: Topic :: Multimedia :: Sound/Audio :: Speech
Classifier: Operating System :: MacOS
Requires-Python: >=3.9
License-File: LICENSE
Requires-Dist: setuptools>=65.0.0
Requires-Dist: wheel>=0.38.0
Requires-Dist: pip>=22.0.0
Requires-Dist: tqdm>=4.65.0
Requires-Dist: cffi>=1.15.0
Requires-Dist: regex>=2022.0.0
Requires-Dist: requests>=2.28.0
Requires-Dist: urllib3>=1.26.19
Requires-Dist: certifi>=2022.0.0
Requires-Dist: charset-normalizer>=2.0.0
Requires-Dist: idna>=3.0
Requires-Dist: filelock>=3.0.0
Requires-Dist: packaging>=21.0
Requires-Dist: pyyaml>=6.0
Requires-Dist: typing-extensions>=4.0.0
Requires-Dist: numpy>=1.20.0
Requires-Dist: pyaudio>=0.2.11
Requires-Dist: mlx>=0.0.4
Requires-Dist: librosa<0.11.0,>=0.10.1
Requires-Dist: numba>=0.57.0
Requires-Dist: tiktoken>=0.3.0
Requires-Dist: huggingface_hub<0.21.0,>=0.15.1
Requires-Dist: webrtcvad>=2.0.10
Requires-Dist: torch>=2.0.0
Requires-Dist: torchaudio>=2.0.0
Requires-Dist: scipy>=1.8.0
Requires-Dist: soundfile>=0.10.3
Requires-Dist: colorama>=0.4.4
Requires-Dist: onnxruntime>=1.15.0
Requires-Dist: pvporcupine>=3.0.0
Requires-Dist: fastapi>=0.104.0
Requires-Dist: distro>=1.9.0
Requires-Dist: uvicorn>=0.24.0
Requires-Dist: pydantic>=2.4.0
Requires-Dist: pydantic-core>=2.0.0
Requires-Dist: websockets>=12.0
Requires-Dist: starlette>=0.27.0
Requires-Dist: annotated-types>=0.4.0
Requires-Dist: anyio>=3.3.0
Requires-Dist: sniffio>=1.0.0
Requires-Dist: click>=7.0.0
Requires-Dist: h11>=0.8.0
Requires-Dist: httptools>=0.5.0
Requires-Dist: python-dotenv>=0.13
Requires-Dist: uvloop>=0.14.0; sys_platform != "win32" and implementation_name == "cpython"
Requires-Dist: watchfiles>=0.13
Requires-Dist: websocket-client>=1.4.0
Requires-Dist: httpx>=0.23.0
Requires-Dist: httpcore>=0.15.0
Requires-Dist: orjson>=3.8.0
Requires-Dist: typing_inspect>=0.8.0
Requires-Dist: typing_inspection>=0.1.0
Requires-Dist: openai>=1.82.0
Requires-Dist: jiter>=0.7.0
Provides-Extra: openai
Requires-Dist: openai>=1.82.0; extra == "openai"
Requires-Dist: websocket-client>=1.4.0; extra == "openai"
Requires-Dist: requests>=2.28.0; extra == "openai"
Requires-Dist: distro>=1.9.0; extra == "openai"
Provides-Extra: wakeword
Provides-Extra: server
Requires-Dist: fastapi>=0.104.0; extra == "server"
Requires-Dist: uvicorn>=0.24.0; extra == "server"
Requires-Dist: pydantic>=2.4.0; extra == "server"
Requires-Dist: websockets>=12.0; extra == "server"
Provides-Extra: dev
Requires-Dist: pytest>=7.0.0; extra == "dev"
Requires-Dist: black>=23.0.0; extra == "dev"
Requires-Dist: isort>=5.12.0; extra == "dev"
Requires-Dist: mypy>=1.0.0; extra == "dev"
Requires-Dist: setuptools>=65.0.0; extra == "dev"
Dynamic: license-file
